flowcell
