Metadata-Version: 1.1
Name: flowcell
Version: 0.0.5
Summary: Acquisition software for wireless flow-through spectrophotometer
Home-page: https://gitlab.com/william.belanger/flowcell
Author: William Belanger
Author-email: UNKNOWN
License: UNKNOWN
Keywords: spectrometry photometer spectrophotometer uv-vis hc05 opt101 biotechnology
Platform: UNKNOWN
Classifier: License :: OSI Approved :: GNU General Public License v3 (GPLv3)
Classifier: Programming Language :: Python :: 3.6
Classifier: Operating System :: POSIX :: Linux
Classifier: Operating System :: Microsoft :: Windows :: Windows 10
